eadapters/__init__.py
eadapters/base.py
eadapters/budy_a.py
eadapters/factory.py
eadapters/models/__init__.py
eadapters/models/_return.py
eadapters/models/account.py
eadapters/models/address.py
eadapters/models/bag.py
eadapters/models/bag_line.py
eadapters/models/base.py
eadapters/models/brand.py
eadapters/models/card_payment_method.py
eadapters/models/category.py
eadapters/models/city.py
eadapters/models/collection.py
eadapters/models/color.py
eadapters/models/country.py
eadapters/models/credit.py
eadapters/models/credit_card.py
eadapters/models/currency.py
eadapters/models/graphic.py
eadapters/models/group.py
eadapters/models/mbway.py
eadapters/models/merchant.py
eadapters/models/order.py
eadapters/models/order_line.py
eadapters/models/payment.py
eadapters/models/payment_method.py
eadapters/models/product.py
eadapters/models/referral.py
eadapters/models/season.py
eadapters/models/section.py
eadapters/models/shipping_option.py
eadapters/models/state.py
eadapters/models/store.py
eadapters/models/subscription.py
eadapters/models/voucher.py
eadapters/models/wishlist.py
eadapters/models/wishlist_line.py
eadapters/models/budy/__init__.py
eadapters/models/budy/bd_account.py
eadapters/models/budy/bd_address.py
eadapters/models/budy/bd_bag.py
eadapters/models/budy/bd_bag_line.py
eadapters/models/budy/bd_brand.py
eadapters/models/budy/bd_card_payment_method.py
eadapters/models/budy/bd_category.py
eadapters/models/budy/bd_city.py
eadapters/models/budy/bd_collection.py
eadapters/models/budy/bd_color.py
eadapters/models/budy/bd_common.py
eadapters/models/budy/bd_country.py
eadapters/models/budy/bd_credit.py
eadapters/models/budy/bd_group.py
eadapters/models/budy/bd_merchant.py
eadapters/models/budy/bd_order.py
eadapters/models/budy/bd_order_line.py
eadapters/models/budy/bd_payment.py
eadapters/models/budy/bd_payment_method.py
eadapters/models/budy/bd_product.py
eadapters/models/budy/bd_referral.py
eadapters/models/budy/bd_return.py
eadapters/models/budy/bd_season.py
eadapters-0.4.4.dist-info/METADATA
eadapters-0.4.4.dist-info/WHEEL
eadapters-0.4.4.dist-info/top_level.txt
eadapters-0.4.4.dist-info/RECORD
